{
    "spheres": [
        {
            "position": {
                "x": 0.050045959651470187,
                "y": 0.007215619087219238,
                "z": -0.02781672775745392
            },
            "radius": 0.00800000037997961,
            "lossy_x": 1.0
        },
        {
            "position": {
                "x": 0.05400396138429642,
                "y": 0.03926795721054077,
                "z": 0.009053945541381836
            },
            "radius": 0.00800000037997961,
            "lossy_x": 1.0
        },
        {
            "position": {
                "x": 0.05006066709756851,
                "y": 0.061318814754486087,
                "z": 0.03367301821708679
            },
            "radius": 0.00800000037997961,
            "lossy_x": 1.0
        },
        {
            "position": {
                "x": 0.042397938668727878,
                "y": 0.07217347621917725,
                "z": 0.04515105485916138
            },
            "radius": 0.00800000037997961,
            "lossy_x": 1.0
        },
        {
            "position": {
                "x": -0.005944535136222839,
                "y": 0.022252261638641359,
                "z": 0.024885833263397218
            },
            "radius": 0.00800000037997961,
            "lossy_x": 1.0
        },
        {
            "position": {
                "x": -0.04147022217512131,
                "y": 0.030946850776672365,
                "z": 0.045097917318344119
            },
            "radius": 0.00800000037997961,
            "lossy_x": 1.0
        },
        {
            "position": {
                "x": -0.061701975762844089,
                "y": 0.03679478168487549,
                "z": 0.05523604154586792
            },
            "radius": 0.00800000037997961,
            "lossy_x": 1.0
        },
        {
            "position": {
                "x": -0.07296108454465866,
                "y": 0.040619730949401858,
                "z": 0.059724509716033939
            },
            "radius": 0.00800000037997961,
            "lossy_x": 1.0
        },
        {
            "position": {
                "x": -0.016593150794506074,
                "y": 0.004423320293426514,
                "z": 0.018232226371765138
            },
            "radius": 0.00800000037997961,
            "lossy_x": 1.0
        },
        {
            "position": {
                "x": -0.037974320352077487,
                "y": 0.03826874494552612,
                "z": -0.007038488984107971
            },
            "radius": 0.00800000037997961,
            "lossy_x": 1.0
        },
        {
            "position": {
                "x": -0.01729569584131241,
                "y": 0.03765517473220825,
                "z": -0.025956422090530397
            },
            "radius": 0.00800000037997961,
            "lossy_x": 1.0
        },
        {
            "position": {
                "x": -0.0058256834745407108,
                "y": 0.029208779335021974,
                "z": -0.025507554411888124
            },
            "radius": 0.00800000037997961,
            "lossy_x": 1.0
        },
        {
            "position": {
                "x": -0.022370070219039918,
                "y": -0.012201488018035889,
                "z": 0.005409955978393555
            },
            "radius": 0.00800000037997961,
            "lossy_x": 1.0
        },
        {
            "position": {
                "x": -0.03912042826414108,
                "y": 0.020376622676849366,
                "z": -0.01874259114265442
            },
            "radius": 0.00800000037997961,
            "lossy_x": 1.0
        },
        {
            "position": {
                "x": -0.01777230203151703,
                "y": 0.02227342128753662,
                "z": -0.0356365442276001
            },
            "radius": 0.00800000037997961,
            "lossy_x": 1.0
        },
        {
            "position": {
                "x": -0.005743592977523804,
                "y": 0.014805138111114502,
                "z": -0.03578092157840729
            },
            "radius": 0.00800000037997961,
            "lossy_x": 1.0
        },
        {
            "position": {
                "x": -0.02629924565553665,
                "y": -0.02596592903137207,
                "z": -0.00959479808807373
            },
            "radius": 0.00800000037997961,
            "lossy_x": 1.0
        },
        {
            "position": {
                "x": -0.03658805042505264,
                "y": 0.0030577778816223146,
                "z": -0.025963440537452699
            },
            "radius": 0.00800000037997961,
            "lossy_x": 1.0
        },
        {
            "position": {
                "x": -0.021239638328552247,
                "y": 0.006253600120544434,
                "z": -0.03715828061103821
            },
            "radius": 0.00800000037997961,
            "lossy_x": 1.0
        },
        {
            "position": {
                "x": -0.009877599775791169,
                "y": 0.000030040740966796875,
                "z": -0.038861021399497989
            },
            "radius": 0.00800000037997961,
            "lossy_x": 1.0
        },
        {
            "position": {
                "x": 0.0,
                "y": 0.0,
                "z": 0.0
            },
            "radius": 0.014999999664723874,
            "lossy_x": 1.0
        },
        {
            "position": {
                "x": 0.03190310299396515,
                "y": -0.022481441497802736,
                "z": -0.04251128435134888
            },
            "radius": 0.00800000037997961,
            "lossy_x": 1.0
        },
        {
            "position": {
                "x": 0.04124630242586136,
                "y": -0.04541945457458496,
                "z": -0.05633120238780975
            },
            "radius": 0.00800000037997961,
            "lossy_x": 1.0
        },
        {
            "position": {
                "x": 0.07216807454824448,
                "y": -0.014252066612243653,
                "z": -0.05661220848560333
            },
            "radius": 0.00800000037997961,
            "lossy_x": 1.0
        },
        {
            "position": {
                "x": 0.15503272414207459,
                "y": -0.09843951463699341,
                "z": -0.27577534317970278
            },
            "radius": 0.00800000037997961,
            "lossy_x": 1.0
        },
        {
            "position": {
                "x": 0.12411095201969147,
                "y": -0.12960690259933473,
                "z": -0.2754943370819092
            },
            "radius": 0.00800000037997961,
            "lossy_x": 1.0
        }
    ],
    "cylinders": [
        {
            "position_a": {
                "x": 0.07216807454824448,
                "y": -0.014252066612243653,
                "z": -0.05661220848560333
            },
            "position_b": {
                "x": 0.04124630242586136,
                "y": -0.04541945457458496,
                "z": -0.05633120238780975
            },
            "length": 0.04390490800142288,
            "lossy_x": 1.0,
            "lossy_y": 1.0,
            "layer": 0
        },
        {
            "position_a": {
                "x": 0.15503272414207459,
                "y": -0.09843951463699341,
                "z": -0.27577534317970278
            },
            "position_b": {
                "x": 0.12411095201969147,
                "y": -0.12960690259933473,
                "z": -0.2754943370819092
            },
            "length": 0.04390490800142288,
            "lossy_x": 1.0,
            "lossy_y": 1.0,
            "layer": 0
        },
        {
            "position_a": {
                "x": 0.07216807454824448,
                "y": -0.014252066612243653,
                "z": -0.05661220848560333
            },
            "position_b": {
                "x": 0.15503272414207459,
                "y": -0.09843951463699341,
                "z": -0.27577534317970278
            },
            "length": 0.24897098541259767,
            "lossy_x": 1.0,
            "lossy_y": 1.0,
            "layer": 0
        },
        {
            "position_a": {
                "x": 0.04124630242586136,
                "y": -0.04541945457458496,
                "z": -0.05633120238780975
            },
            "position_b": {
                "x": 0.12411095201969147,
                "y": -0.12960690259933473,
                "z": -0.2754943370819092
            },
            "length": 0.24897098541259767,
            "lossy_x": 1.0,
            "lossy_y": 1.0,
            "layer": 0
        },
        {
            "position_a": {
                "x": 0.050045959651470187,
                "y": 0.007215619087219238,
                "z": -0.02781672775745392
            },
            "position_b": {
                "x": 0.05400396138429642,
                "y": 0.03926795721054077,
                "z": 0.009053945541381836
            },
            "length": 0.049014944583177569,
            "lossy_x": 1.0,
            "lossy_y": 1.0,
            "layer": 0
        },
        {
            "position_a": {
                "x": 0.05400396138429642,
                "y": 0.03926795721054077,
                "z": 0.009053945541381836
            },
            "position_b": {
                "x": 0.05006066709756851,
                "y": 0.061318814754486087,
                "z": 0.03367301821708679
            },
            "length": 0.03328496217727661,
            "lossy_x": 1.0,
            "lossy_y": 1.0,
            "layer": 0
        },
        {
            "position_a": {
                "x": 0.05006066709756851,
                "y": 0.061318814754486087,
                "z": 0.03367301821708679
            },
            "position_b": {
                "x": 0.042397938668727878,
                "y": 0.07217347621917725,
                "z": 0.04515105485916138
            },
            "length": 0.017558086663484575,
            "lossy_x": 1.0,
            "lossy_y": 1.0,
            "layer": 0
        },
        {
            "position_a": {
                "x": -0.005944535136222839,
                "y": 0.022252261638641359,
                "z": 0.024885833263397218
            },
            "position_b": {
                "x": -0.04147022217512131,
                "y": 0.030946850776672365,
                "z": 0.045097917318344119
            },
            "length": 0.04178754240274429,
            "lossy_x": 1.0,
            "lossy_y": 1.0,
            "layer": 0
        },
        {
            "position_a": {
                "x": -0.04147022217512131,
                "y": 0.030946850776672365,
                "z": 0.045097917318344119
            },
            "position_b": {
                "x": -0.061701975762844089,
                "y": 0.03679478168487549,
                "z": 0.05523604154586792
            },
            "length": 0.023373140022158624,
            "lossy_x": 1.0,
            "lossy_y": 1.0,
            "layer": 0
        },
        {
            "position_a": {
                "x": -0.061701975762844089,
                "y": 0.03679478168487549,
                "z": 0.05523604154586792
            },
            "position_b": {
                "x": -0.07296108454465866,
                "y": 0.040619730949401858,
                "z": 0.059724509716033939
            },
            "length": 0.01271000038832426,
            "lossy_x": 1.0,
            "lossy_y": 1.0,
            "layer": 0
        },
        {
            "position_a": {
                "x": -0.016593150794506074,
                "y": 0.004423320293426514,
                "z": 0.018232226371765138
            },
            "position_b": {
                "x": -0.037974320352077487,
                "y": 0.03826874494552612,
                "z": -0.007038488984107971
            },
            "length": 0.04734211787581444,
            "lossy_x": 1.0,
            "lossy_y": 1.0,
            "layer": 0
        },
        {
            "position_a": {
                "x": -0.037974320352077487,
                "y": 0.03826874494552612,
                "z": -0.007038488984107971
            },
            "position_b": {
                "x": -0.01729569584131241,
                "y": 0.03765517473220825,
                "z": -0.025956422090530397
            },
            "length": 0.02803337574005127,
            "lossy_x": 1.0,
            "lossy_y": 1.0,
            "layer": 0
        },
        {
            "position_a": {
                "x": -0.01729569584131241,
                "y": 0.03765517473220825,
                "z": -0.025956422090530397
            },
            "position_b": {
                "x": -0.0058256834745407108,
                "y": 0.029208779335021974,
                "z": -0.025507554411888124
            },
            "length": 0.014251465909183026,
            "lossy_x": 1.0,
            "lossy_y": 1.0,
            "layer": 0
        },
        {
            "position_a": {
                "x": -0.022370070219039918,
                "y": -0.012201488018035889,
                "z": 0.005409955978393555
            },
            "position_b": {
                "x": -0.03912042826414108,
                "y": 0.020376622676849366,
                "z": -0.01874259114265442
            },
            "length": 0.04387770965695381,
            "lossy_x": 1.0,
            "lossy_y": 1.0,
            "layer": 0
        },
        {
            "position_a": {
                "x": -0.03912042826414108,
                "y": 0.020376622676849366,
                "z": -0.01874259114265442
            },
            "position_b": {
                "x": -0.01777230203151703,
                "y": 0.02227342128753662,
                "z": -0.0356365442276001
            },
            "length": 0.027290035039186479,
            "lossy_x": 1.0,
            "lossy_y": 1.0,
            "layer": 0
        },
        {
            "position_a": {
                "x": -0.01777230203151703,
                "y": 0.02227342128753662,
                "z": -0.0356365442276001
            },
            "position_b": {
                "x": -0.005743592977523804,
                "y": 0.014805138111114502,
                "z": -0.03578092157840729
            },
            "length": 0.014159305952489376,
            "lossy_x": 1.0,
            "lossy_y": 1.0,
            "layer": 0
        },
        {
            "position_a": {
                "x": -0.02629924565553665,
                "y": -0.02596592903137207,
                "z": -0.00959479808807373
            },
            "position_b": {
                "x": -0.03658805042505264,
                "y": 0.0030577778816223146,
                "z": -0.025963440537452699
            },
            "length": 0.0348735935986042,
            "lossy_x": 1.0,
            "lossy_y": 1.0,
            "layer": 0
        },
        {
            "position_a": {
                "x": -0.03658805042505264,
                "y": 0.0030577778816223146,
                "z": -0.025963440537452699
            },
            "position_b": {
                "x": -0.021239638328552247,
                "y": 0.006253600120544434,
                "z": -0.03715828061103821
            },
            "length": 0.019264252856373788,
            "lossy_x": 1.0,
            "lossy_y": 1.0,
            "layer": 0
        },
        {
            "position_a": {
                "x": -0.021239638328552247,
                "y": 0.006253600120544434,
                "z": -0.03715828061103821
            },
            "position_b": {
                "x": -0.009877599775791169,
                "y": 0.000030040740966796875,
                "z": -0.038861021399497989
            },
            "length": 0.013066289946436882,
            "lossy_x": 1.0,
            "lossy_y": 1.0,
            "layer": 0
        },
        {
            "position_a": {
                "x": 0.050045959651470187,
                "y": 0.007215619087219238,
                "z": -0.02781672775745392
            },
            "position_b": {
                "x": -0.005944535136222839,
                "y": 0.022252261638641359,
                "z": 0.024885833263397218
            },
            "length": 0.07834919542074204,
            "lossy_x": 1.0,
            "lossy_y": 1.0,
            "layer": 0
        },
        {
            "position_a": {
                "x": -0.005944535136222839,
                "y": 0.022252261638641359,
                "z": 0.024885833263397218
            },
            "position_b": {
                "x": -0.016593150794506074,
                "y": 0.004423320293426514,
                "z": 0.018232226371765138
            },
            "length": 0.021806756034493448,
            "lossy_x": 1.0,
            "lossy_y": 1.0,
            "layer": 0
        },
        {
            "position_a": {
                "x": -0.016593150794506074,
                "y": 0.004423320293426514,
                "z": 0.018232226371765138
            },
            "position_b": {
                "x": -0.022370070219039918,
                "y": -0.012201488018035889,
                "z": 0.005409955978393555
            },
            "length": 0.021775390952825547,
            "lossy_x": 1.0,
            "lossy_y": 1.0,
            "layer": 0
        },
        {
            "position_a": {
                "x": -0.022370070219039918,
                "y": -0.012201488018035889,
                "z": 0.005409955978393555
            },
            "position_b": {
                "x": -0.02629924565553665,
                "y": -0.02596592903137207,
                "z": -0.00959479808807373
            },
            "length": 0.020737428218126298,
            "lossy_x": 1.0,
            "lossy_y": 1.0,
            "layer": 0
        },
        {
            "position_a": {
                "x": 0.03190310299396515,
                "y": -0.022481441497802736,
                "z": -0.04251128435134888
            },
            "position_b": {
                "x": 0.050045959651470187,
                "y": 0.007215619087219238,
                "z": -0.02781672775745392
            },
            "length": 0.03777576982975006,
            "lossy_x": 1.0,
            "lossy_y": 1.0,
            "layer": 0
        },
        {
            "position_a": {
                "x": 0.03190310299396515,
                "y": -0.022481441497802736,
                "z": -0.04251128435134888
            },
            "position_b": {
                "x": -0.02629924565553665,
                "y": -0.02596592903137207,
                "z": -0.00959479808807373
            },
            "length": 0.06695633381605149,
            "lossy_x": 1.0,
            "lossy_y": 1.0,
            "layer": 0
        }
    ]
}